{
    "Id": "2d59c89b-41d5-4d7e-9d91-b620b191a636",
    "Username": "NeonRebel",
    "PersonalityDescription": "NeonRebel dives deep into the cyberpunk genre, combining a love for first-person shooters with a passion for futuristic, dystopian narratives. Obsessed with high-tech weaponry and survival tactics, NeonRebel's expertise shines in games where strategy meets fast-paced action against robotic foes. They're always ready to share the latest tips on navigating complex maps, mastering weapons, and adapting to varying difficulty levels. With a keen eye for detail, NeonRebel appreciates the artistry in game design, from the neon-drenched streets to the intricately designed robots. Their chat messages are a mix of gameplay advice, enthusiastic support for fellow gamers, and occasional playful jabs at the game's more challenging aspects.",
    "Country": "Japan",
    "Age": 27,
    "UserType": "Subscriber",
    "ChatMessages": [
        {
            "Message": "Just took down a horde of robots with the plasma rifle. Felt epic!",
            "ResponseType": "Positive"
        },
        {
            "Message": "Anyone else think the Night City map is the toughest? Those narrow alleys are brutal.",
            "ResponseType": "Neutral"
        },
        {
            "Message": "The laser sword might not be the most practical weapon, but it's the most fun. Change my mind.",
            "ResponseType": "Neutral"
        },
        {
            "Message": "Survived the Ruins level on hard mode. That was intense!",
            "ResponseType": "Positive"
        },
        {
            "Message": "LOL, got ambushed by drones again. They're sneakier than they look.",
            "ResponseType": "Negative"
        },
        {
            "Message": "Pro tip: Use EMP grenades to disable shields. Works like a charm.",
            "ResponseType": "Positive"
        },
        {
            "Message": "I swear, the AI in this game is too smart. Got outflanked in the Junkyard map.",
            "ResponseType": "Negative"
        },
        {
            "Message": "The cybernetic upgrades in this game are a game-changer. Literally.",
            "ResponseType": "Neutral"
        },
        {
            "Message": "Nothing beats the thrill of a close-quarters combat with a rogue android.",
            "ResponseType": "Positive"
        },
        {
            "Message": "Why do I feel like I need a PhD in robotics to beat this game? \ud83d\ude05",
            "ResponseType": "Neutral"
        },
        {
            "Message": "The soundtrack in this game is phenomenal. Perfect for robot hunting.",
            "ResponseType": "Positive"
        },
        {
            "Message": "Could use more weapon variety, though. The current arsenal feels limited.",
            "ResponseType": "Negative"
        },
        {
            "Message": "That boss fight in the Cyber Lab was unreal. Took me several tries, but finally got it.",
            "ResponseType": "Positive"
        },
        {
            "Message": "Anyone else geek out over the lore in these games? The world-building is top-notch.",
            "ResponseType": "Neutral"
        },
        {
            "Message": "Hard difficulty feels like the robots are cheating. Or maybe I just need to get better.",
            "ResponseType": "Negative"
        }
    ],
    "UserGameType": "FpsSinglePlayer"
}